mycalc/setup.py
dss06023calc-1.0.1.dist-info/METADATA
dss06023calc-1.0.1.dist-info/WHEEL
dss06023calc-1.0.1.dist-info/top_level.txt
dss06023calc-1.0.1.dist-info/RECORD
