Metadata-Version: 2.1
Name: dss06023calc
Version: 1.0.1
Summary: oss-dev my calculator 0001
Home-page: https://github.com/dss06023/dss06023calc
Download-URL: https://github.com/dss06023/dss06023calc/archive/refs/tags/v1.0.1.zip
Author: leeseunggeun
Author-email: dss06023@gmail.com
License: UNKNOWN
Platform: UNKNOWN
